zbase32/__init__.py
python_zbase32-0.1.1.dist-info/LICENSE
python_zbase32-0.1.1.dist-info/WHEEL
python_zbase32-0.1.1.dist-info/METADATA
python_zbase32-0.1.1.dist-info/RECORD
