Metadata-Version: 2.1
Name: python-zbase32
Version: 0.1.1
Summary: A human-oriented base-32 encoding.
Home-page: https://github.com/artisanofcode/python-zbase32
License: MIT
Author: Daniel Knell
Author-email: contact@danielknell.co.uk
Requires-Python: >=3.10,<4.0
Classifier: License :: OSI Approved :: MIT License
Classifier: Programming Language :: Python :: 3
Classifier: Programming Language :: Python :: 3.10
Project-URL: Repository, https://github.com/artisanofcode/python-zbase32
